py_avdu/__init__.py
py_avdu/__main__.py
py_avdu/decrypted_classes.py
py_avdu/encrypted_classes.py
py_avdu/main.py
py_avdu/py.typed
py_avdu-0.0.3.dist-info/METADATA
py_avdu-0.0.3.dist-info/WHEEL
py_avdu-0.0.3.dist-info/entry_points.txt
py_avdu-0.0.3.dist-info/licenses/LICENSE.txt
py_avdu-0.0.3.dist-info/RECORD
