Metadata-Version: 2.4
Name: py-avdu
Version: 0.0.3
Summary: A Python port of Avdu, A utility to view one-time passwords generated from Aegis Authenticator backups. 
Project-URL: Source code, https://github.com/JamesParrott/py-avdu
Project-URL: Bug Tracker, https://github.com/JamesParrott/py-avdu/issues
Author-email: Sammy-T <cyam9019@gmail.com>, "Claude 3.7 Sonnet" <claude.3.7@anthropic.com>
Maintainer-email: James Parrott <james@jamesparrott.dev>
License-Expression: AGPL-3.0-or-later
License-File: LICENSE.txt
Requires-Python: >=3.12
Requires-Dist: cryptography
Requires-Dist: pydantic
Requires-Dist: pyotp
Provides-Extra: types
Requires-Dist: types-cryptography; extra == 'types'
